tap_tripactions/__init__.py
tap_tripactions/client.py
tap_tripactions/streams.py
tap_tripactions/schemas/bookings.json
twilio_tap_tripactions-0.0.2.dist-info/LICENSE
twilio_tap_tripactions-0.0.2.dist-info/METADATA
twilio_tap_tripactions-0.0.2.dist-info/WHEEL
twilio_tap_tripactions-0.0.2.dist-info/entry_points.txt
twilio_tap_tripactions-0.0.2.dist-info/top_level.txt
twilio_tap_tripactions-0.0.2.dist-info/RECORD
